Metadata-Version: 2.1
Name: timing-asgi-statsd
Version: 0.4.0
Summary: ASGI middleware to emit timing metrics with something like statsd
License: MIT
Author: Nikita Konin
Author-email: awesome@nkonin.me
Requires-Python: >=3.8,<4.0
Classifier: License :: OSI Approved :: MIT License
Classifier: Programming Language :: Python :: 3
Classifier: Programming Language :: Python :: 3.8
Classifier: Programming Language :: Python :: 3.9
Requires-Dist: alog (>=0.9.13,<0.10.0)
